morphospaces/__init__.py
morphospaces/_version.py
morphospaces/cli/__init__.py
morphospaces/cli/main.py
morphospaces/cli/skeletonize_cli.py
morphospaces/data/__init__.py
morphospaces/data/data_utils.py
morphospaces/data/skeleton.py
morphospaces/datasets/__init__.py
morphospaces/datasets/_base.py
morphospaces/datasets/hdf5.py
morphospaces/datasets/utils.py
morphospaces/datasets/zarr.py
morphospaces/datasets/_tests/__init__.py
morphospaces/datasets/_tests/test_hdf5.py
morphospaces/datasets/_tests/test_utils.py
morphospaces/io/__init__.py
morphospaces/io/hdf5.py
morphospaces/logging/__init__.py
morphospaces/logging/image.py
morphospaces/losses/__init__.py
morphospaces/losses/embedding.py
morphospaces/losses/regression.py
morphospaces/losses/segmentation.py
morphospaces/losses/skeletonization.py
morphospaces/losses/util.py
morphospaces/losses/_tests/__init__.py
morphospaces/losses/_tests/test_embedding.py
morphospaces/losses/_tests/test_skeletonization.py
morphospaces/networks/__init__.py
morphospaces/networks/constants.py
morphospaces/networks/multiscale_skeletonization.py
morphospaces/networks/pixel_embedding.py
morphospaces/networks/semantic_multiscale.py
morphospaces/networks/semantic_swin_unetr.py
morphospaces/networks/semantic_unet.py
morphospaces/networks/skeletonization.py
morphospaces/networks/swin_unetr.py
morphospaces/networks/unet.py
morphospaces/networks/unetr.py
morphospaces/networks/vit_autoencoder.py
morphospaces/networks/_components/__init__.py
morphospaces/networks/_components/embedding_swin_unetr.py
morphospaces/networks/_components/memory_bank.py
morphospaces/networks/_components/unet_blocks.py
morphospaces/networks/_components/unet_model.py
morphospaces/networks/_components/_tests/__init__.py
morphospaces/networks/_components/_tests/test_memory_bank.py
morphospaces/training/__init__.py
morphospaces/training/multiscale_skeletonization.py
morphospaces/transforms/__init__.py
morphospaces/transforms/image.py
morphospaces/transforms/label.py
morphospaces-0.0.7.dist-info/licenses/LICENSE
morphospaces-0.0.7.dist-info/METADATA
morphospaces-0.0.7.dist-info/WHEEL
morphospaces-0.0.7.dist-info/entry_points.txt
morphospaces-0.0.7.dist-info/top_level.txt
morphospaces-0.0.7.dist-info/RECORD
