Metadata-Version: 2.4
Name: morphospaces
Version: 0.0.7
Summary: a library for creating  and exploring morphospaces.
Author-email: Kevin Yamauchi <kevin.yamauchi@gmail.com>
License: BSD-3-Clause
Project-URL: Homepage, https://github.com/morphometrics/morphospaces
Project-URL: Bug Tracker, https://github.com/morphometrics/morphospace/issues
Project-URL: Documentation, https://github.com/morphometrics/morphospace#README.md
Project-URL: Source Code, https://github.com/morphometrics/morphospace
Project-URL: User Support, https://github.com/morphometrics/morphospace/issues
Classifier: Development Status :: 2 - Pre-Alpha
Classifier: Intended Audience :: Developers
Classifier: License :: OSI Approved :: BSD License
Classifier: Operating System :: OS Independent
Classifier: Programming Language :: Python
Classifier: Programming Language :: Python :: 3
Classifier: Programming Language :: Python :: 3 :: Only
Classifier: Programming Language :: Python :: 3.8
Classifier: Programming Language :: Python :: 3.9
Classifier: Programming Language :: Python :: 3.10
Classifier: Topic :: Scientific/Engineering :: Image Processing
Requires-Python: >=3.8
License-File: LICENSE
Requires-Dist: dask
Requires-Dist: einops
Requires-Dist: h5py
Requires-Dist: magicgui
Requires-Dist: monai
Requires-Dist: numpy
Requires-Dist: pytorch-lightning
Requires-Dist: qtpy
Requires-Dist: rich
Requires-Dist: scikit-image
Requires-Dist: scipy
Requires-Dist: tensorboard
Requires-Dist: torch
Requires-Dist: torchvision
Requires-Dist: typer
Provides-Extra: testing
Requires-Dist: napari; extra == "testing"
Requires-Dist: pyqt5; extra == "testing"
Requires-Dist: pytest; extra == "testing"
Requires-Dist: pytest-cov; extra == "testing"
Requires-Dist: pytest-qt; extra == "testing"
Requires-Dist: tox; extra == "testing"
Dynamic: license-file
